nislmigrate/__init__.py
nislmigrate/argument_handler.py
nislmigrate/extensibility/__init__.py
nislmigrate/extensibility/migrator_plugin.py
nislmigrate/extensibility/migrator_plugin_loader.py
nislmigrate/facades/__init__.py
nislmigrate/facades/facade_factory.py
nislmigrate/facades/file_system_facade.py
nislmigrate/facades/mongo_configuration.py
nislmigrate/facades/mongo_facade.py
nislmigrate/facades/ni_web_server_manager_facade.py
nislmigrate/facades/process_facade.py
nislmigrate/facades/system_link_service_manager_facade.py
nislmigrate/logs/__init__.py
nislmigrate/logs/logging_setup.py
nislmigrate/logs/migration_error.py
nislmigrate/migration_action.py
nislmigrate/migration_facilitator.py
nislmigrate/migration_tool.py
nislmigrate/migrators/__init__.py
nislmigrate/migrators/alarm_migrator.py
nislmigrate/migrators/asset_migrator.py
nislmigrate/migrators/asset_rule_engine_migrator.py
nislmigrate/migrators/document_manager_migrator.py
nislmigrate/migrators/file_migrator.py
nislmigrate/migrators/notification_migrator.py
nislmigrate/migrators/repository_migrator.py
nislmigrate/migrators/security_migrator.py
nislmigrate/migrators/system_states_migrator.py
nislmigrate/migrators/systems_management_migrator.py
nislmigrate/migrators/tag_migrator.py
nislmigrate/migrators/tag_rule_engine_migrator.py
nislmigrate/migrators/test_monitor_migrator.py
nislmigrate/migrators/user_data_migrator.py
nislmigrate/utility/__init__.py
nislmigrate/utility/information_logger.py
nislmigrate/utility/paths.py
nislmigrate/utility/permission_checker.py
nislmigrate-1.1.0.dist-info/entry_points.txt
nislmigrate-1.1.0.dist-info/LICENSE
nislmigrate-1.1.0.dist-info/WHEEL
nislmigrate-1.1.0.dist-info/METADATA
nislmigrate-1.1.0.dist-info/RECORD
