Metadata-Version: 2.1
Name: nislmigrate
Version: 1.1.0
Summary: The tool for migrating SystemLink data.
Author: cnunnall
Author-email: christian.nunnally@ni.com
Requires-Python: >=3.6.8,<4.0.0
Classifier: License :: OSI Approved :: MIT License
Classifier: Programming Language :: Python :: 3
Classifier: Programming Language :: Python :: 3.10
Classifier: Programming Language :: Python :: 3.7
Classifier: Programming Language :: Python :: 3.8
Classifier: Programming Language :: Python :: 3.9
Classifier: Programming Language :: Python :: Implementation :: PyPy
Classifier: Topic :: Software Development :: Libraries :: Python Modules
Requires-Dist: argparse (>=1.4.0,<2.0.0)
Requires-Dist: cryptography (>=35.0.0,<36.0.0)
Requires-Dist: pymongo (>=3.12.1,<4.0.0)
Project-URL: Documentation, https://github.com/ni/NI-SystemLink-Migration
